sdc_scissor/__init__.py
sdc_scissor/can_api/__init__.py
sdc_scissor/can_api/can_bus_handler.py
sdc_scissor/can_api/can_msg_generator.py
sdc_scissor/can_api/can_output.py
sdc_scissor/cli.py
sdc_scissor/config.py
sdc_scissor/feature_extraction_api/__init__.py
sdc_scissor/feature_extraction_api/angle_based_strategy.py
sdc_scissor/feature_extraction_api/equi_distance_strategy.py
sdc_scissor/feature_extraction_api/feature_extraction.py
sdc_scissor/feature_extraction_api/parameterized_uniform_strategy.py
sdc_scissor/feature_extraction_api/road_geometry_calculator.py
sdc_scissor/feature_extraction_api/segmentation_strategy.py
sdc_scissor/machine_learning_api/__init__.py
sdc_scissor/machine_learning_api/cost_effectiveness_evaluator.py
sdc_scissor/machine_learning_api/csv_loader.py
sdc_scissor/machine_learning_api/model_evaluator.py
sdc_scissor/machine_learning_api/predictor.py
sdc_scissor/obstacle_api/__init__.py
sdc_scissor/obstacle_api/beamng_bump.py
sdc_scissor/obstacle_api/beamng_delineator.py
sdc_scissor/obstacle_api/beamng_obstacle_factory.py
sdc_scissor/obstacle_api/beamng_tree.py
sdc_scissor/obstacle_api/bump.py
sdc_scissor/obstacle_api/carla_bump.py
sdc_scissor/obstacle_api/carla_delineator.py
sdc_scissor/obstacle_api/carla_obstacle_factory.py
sdc_scissor/obstacle_api/carla_tree.py
sdc_scissor/obstacle_api/delineator.py
sdc_scissor/obstacle_api/obstacle_factory.py
sdc_scissor/obstacle_api/tree.py
sdc_scissor/sdc_prioritizer/Dockerfile.testPrioritization
sdc_scissor/sdc_prioritizer/README.md
sdc_scissor/sdc_prioritizer/__init__.py
sdc_scissor/sdc_prioritizer/code/faultDetection.m
sdc_scissor/sdc_prioritizer/code/faultDetectionRatePlots.m
sdc_scissor/sdc_prioritizer/code/featureSelection.m
sdc_scissor/sdc_prioritizer/code/fitness.m
sdc_scissor/sdc_prioritizer/code/initialPopulation.m
sdc_scissor/sdc_prioritizer/code/main.m
sdc_scissor/sdc_prioritizer/code/mainGreedy.m
sdc_scissor/sdc_prioritizer/code/objectives.m
sdc_scissor-2.2.3.dist-info/LICENSE.md
sdc_scissor-2.2.3.dist-info/METADATA
sdc_scissor-2.2.3.dist-info/WHEEL
sdc_scissor-2.2.3.dist-info/entry_points.txt
sdc_scissor-2.2.3.dist-info/RECORD
