Metadata-Version: 2.1
Name: SDC-Scissor
Version: 2.2.3
Summary: A cost-effective test selection for self-driving cars in virtual environments
Home-page: https://github.com/ChristianBirchler/sdc-scissor
License: GPL-3.0-or-later
Author: Christian Birchler
Author-email: birchler.chr@gmail.com
Requires-Python: >=3.10,<3.11
Classifier: License :: OSI Approved :: GNU General Public License v3 or later (GPLv3+)
Classifier: Programming Language :: Python :: 3
Classifier: Programming Language :: Python :: 3.10
Requires-Dist: PyYAML (>=6.0,<7.0)
Requires-Dist: Shapely (>=1.8.1,<2.0.0)
Requires-Dist: beamngpy (==1.22)
Requires-Dist: cantools (>=38.0.1,<39.0.0)
Requires-Dist: click (>=8.0.4,<9.0.0)
Requires-Dist: icontract (>=2.6.2,<3.0.0)
Requires-Dist: influxdb-client (>=1.36.1,<2.0.0)
Requires-Dist: pandas (>=1.4.1,<2.0.0)
Requires-Dist: pymoo (==0.4.2.2)
Requires-Dist: python-dotenv (>=1.0.0,<2.0.0)
Requires-Dist: scikit-learn (>=1.0.2,<2.0.0)
Project-URL: Documentation, https://sdc-scissor.readthedocs.io/
Project-URL: Repository, https://github.com/ChristianBirchler/sdc-scissor
